ZapRobotHelper/__init__.py
ZapRobotHelper/base/__init__.py
ZapRobotHelper/base/context.py
ZapRobotHelper/base/librarycomponent.py
ZapRobotHelper/base/robotlibcore.py
ZapRobotHelper/keywords/__init__.py
ZapRobotHelper/keywords/zap_api_manager.py
ZapRobotHelper/utils/__init__.py
ZapRobotHelper/utils/browsercache.py
ZapRobotHelper/utils/librarylistener.py
ZapRobotHelper/utils/types.py
ZapRobotHelper/utils/events/__init__.py
ZapRobotHelper/utils/events/event.py
ZapRobotHelper/utils/events/scope_event.py
hydrazaphelper-1.0.0.dist-info/LICENSE
hydrazaphelper-1.0.0.dist-info/METADATA
hydrazaphelper-1.0.0.dist-info/WHEEL
hydrazaphelper-1.0.0.dist-info/top_level.txt
hydrazaphelper-1.0.0.dist-info/RECORD
