Metadata-Version: 2.1
Name: hydrazaphelper
Version: 1.0.0
Summary: A small wrapper for owasp zap
Author: efe.pisirici
Author-email: "efe.pisirici" <efe.pisirici@hotmail.com>
License: Apache License
Classifier: Programming Language :: Python :: 3
Classifier: License :: OSI Approved :: MIT License
Classifier: Operating System :: OS Independent
Requires-Python: >=3.0
License-File: LICENSE
Requires-Dist: requests (>=2.26.0)
Requires-Dist: requests
Requires-Dist: tomli ; python_version > "3.0"
